[
    {
        "types":[
        {
            "id":"DEC",
            "channels":[
                "R", "G", "B"
            ]
        },
        {
            "id":"SR",
            "channels":[
                 "R", "G", "B", "W"
            ]
        },
        {
            "id":"T12",
            "channels":[
                "R", "G", "B", "STROBE", "MACRO", "MACRO_SPEED", "BRIGHTNESS"
            ]
        },
        {
            "id":"COB",
            "channels":[ 
                "BRIGHTNESS", "R", "G", "B", "STROBE", "MACRO", "MACRO_SPEED"
            ]
        }
    ]
    },
    {
        "lights": [
            {
                "id":"chandelier",
                "type":"DEC",
                "address":1
            },
            {
                "id":"forest_wash",
                "type":"SR",
                "address":4
            },
            {
                "id":"castle_wash",
                "type":"T12",
                "address":113
            },
            {
                "id":"stairs_wash",
                "type":"COB",
                "address":20
            },
            {
                "id":"above_crypt",
                "type":"COB",
                "address":127
            },
            {
                "id":"below_crypt",
                "type":"COB",
                "address":135
            }
        ]
    }

]